[{"name": "swamp", "card_type": 1, "mana": [4]}, {"name": "swamp", "card_type": 1, "mana": [4]}, {"name": "swamp", "card_type": 1, "mana": [4]}, {"name": "swamp", "card_type": 1, "mana": [4]}, {"name": "swamp", "card_type": 1, "mana": [4]}, {"name": "swamp", "card_type": 1, "mana": [4]}, {"name": "swamp", "card_type": 1, "mana": [4]}, {"name": "swamp", "card_type": 1, "mana": [4]}, {"name": "swamp", "card_type": 1, "mana": [4]}, {"name": "swamp", "card_type": 1, "mana": [4]}, {"name": "swamp", "card_type": 1, "mana": [4]}, {"name": "forest", "card_type": 1, "mana": [2]}, {"name": "forest", "card_type": 1, "mana": [2]}, {"name": "forest", "card_type": 1, "mana": [2]}, {"name": "forest", "card_type": 1, "mana": [2]}, {"name": "forest", "card_type": 1, "mana": [2]}, {"name": "forest", "card_type": 1, "mana": [2]}, {"name": "forest", "card_type": 1, "mana": [2]}, {"name": "forest", "card_type": 1, "mana": [2]}, {"name": "forest", "card_type": 1, "mana": [2]}, {"name": "forest", "card_type": 1, "mana": [2]}, {"name": "forest", "card_type": 1, "mana": [2]}, {"name": "golgari guildgate", "card_type": 1, "mana": [2, 4]}, {"name": "golgari guildgate", "card_type": 1, "mana": [2, 4]}, {"name": "golgari guildgate", "card_type": 1, "mana": [2, 4]}, {"name": "golgari guildgate", "card_type": 1, "mana": [2, 4]}, {"name": "saproling token", "card_type": 2}, {"name": "saproling token", "card_type": 2}, {"name": "saproling token", "card_type": 2}, {"name": "saproling token", "card_type": 2}, {"name": "saproling token", "card_type": 2}, {"name": "saproling token", "card_type": 2}, {"name": "saproling token", "card_type": 2}, {"name": "saproling token", "card_type": 2}, {"name": "saproling token", "card_type": 2}, {"name": "saproling token", "card_type": 2}, {"name": "saproling token", "card_type": 2}, {"name": "saproling token", "card_type": 2}, {"name": "saproling token", "card_type": 2}, {"name": "saproling token", "card_type": 2}, {"name": "saproling token", "card_type": 2}, {"name": "saproling token", "card_type": 2}, {"name": "saproling token", "card_type": 2}, {"name": "saproling token", "card_type": 2}, {"name": "saproling token", "card_type": 2}, {"name": "saproling token", "card_type": 2}, {"name": "saproling token", "card_type": 2}, {"name": "saproling token", "card_type": 2}, {"name": "saproling token", "card_type": 2}, {"name": "saproling token", "card_type": 2}, {"name": "saproling token", "card_type": 2}, {"name": "saproling token", "card_type": 2}, {"name": "saproling token", "card_type": 2}, {"name": "saproling token", "card_type": 2}, {"name": "saproling token", "card_type": 2}, {"name": "saproling token", "card_type": 2}, {"name": "saproling token", "card_type": 2}, {"name": "saproling token", "card_type": 2}, {"name": "saproling token", "card_type": 2}, {"name": "saproling token", "card_type": 2}]